HowtodoinjavaQitaJiaocheng1Chuyi/README.md
HowtodoinjavaQitaJiaocheng1Chuyi/__init__.py
HowtodoinjavaQitaJiaocheng1Chuyi/__main__.py
HowtodoinjavaQitaJiaocheng1Chuyi/file.epub
HowtodoinjavaQitaJiaocheng1Chuyi/index.html
HowtodoinjavaQitaJiaocheng1Chuyi/css/__init__.py
HowtodoinjavaQitaJiaocheng1Chuyi/css/annotations.css
HowtodoinjavaQitaJiaocheng1Chuyi/css/main.css
HowtodoinjavaQitaJiaocheng1Chuyi/css/normalize.css
HowtodoinjavaQitaJiaocheng1Chuyi/css/popup.css
HowtodoinjavaQitaJiaocheng1Chuyi/font/__init__.py
HowtodoinjavaQitaJiaocheng1Chuyi/font/fontello.eot
HowtodoinjavaQitaJiaocheng1Chuyi/font/fontello.svg
HowtodoinjavaQitaJiaocheng1Chuyi/font/fontello.ttf
HowtodoinjavaQitaJiaocheng1Chuyi/font/fontello.woff
HowtodoinjavaQitaJiaocheng1Chuyi/img/__init__.py
HowtodoinjavaQitaJiaocheng1Chuyi/img/annotator-glyph-sprite.png
HowtodoinjavaQitaJiaocheng1Chuyi/img/annotator-icon-sprite.png
HowtodoinjavaQitaJiaocheng1Chuyi/img/apple-touch-icon.png
HowtodoinjavaQitaJiaocheng1Chuyi/img/cancelfullscreen.png
HowtodoinjavaQitaJiaocheng1Chuyi/img/close.png
HowtodoinjavaQitaJiaocheng1Chuyi/img/fullscreen.png
HowtodoinjavaQitaJiaocheng1Chuyi/img/loader.gif
HowtodoinjavaQitaJiaocheng1Chuyi/img/menu-icon.png
HowtodoinjavaQitaJiaocheng1Chuyi/img/save.png
HowtodoinjavaQitaJiaocheng1Chuyi/img/saved.png
HowtodoinjavaQitaJiaocheng1Chuyi/img/settings-s.png
HowtodoinjavaQitaJiaocheng1Chuyi/img/settings.png
HowtodoinjavaQitaJiaocheng1Chuyi/img/star.png
HowtodoinjavaQitaJiaocheng1Chuyi/js/__init__.py
HowtodoinjavaQitaJiaocheng1Chuyi/js/epub.js
HowtodoinjavaQitaJiaocheng1Chuyi/js/epub.min.js
HowtodoinjavaQitaJiaocheng1Chuyi/js/epub.min.map
HowtodoinjavaQitaJiaocheng1Chuyi/js/hooks.min.js
HowtodoinjavaQitaJiaocheng1Chuyi/js/hooks.min.map
HowtodoinjavaQitaJiaocheng1Chuyi/js/reader.js
HowtodoinjavaQitaJiaocheng1Chuyi/js/reader.js.map
HowtodoinjavaQitaJiaocheng1Chuyi/js/reader.min.js
HowtodoinjavaQitaJiaocheng1Chuyi/js/reader.min.map
HowtodoinjavaQitaJiaocheng1Chuyi/js/hooks/__init__.py
howtodoinjava_qita_jiaocheng_1_chuyi-2024.3.4.0.dist-info/METADATA
howtodoinjava_qita_jiaocheng_1_chuyi-2024.3.4.0.dist-info/WHEEL
howtodoinjava_qita_jiaocheng_1_chuyi-2024.3.4.0.dist-info/entry_points.txt
howtodoinjava_qita_jiaocheng_1_chuyi-2024.3.4.0.dist-info/top_level.txt
howtodoinjava_qita_jiaocheng_1_chuyi-2024.3.4.0.dist-info/RECORD
